django_urlconverter
tests
