Metadata-Version: 1.0
Name: django-urlconverter
Version: 1.0.0
Summary: Django URL converters
Home-page: UNKNOWN
Author: Paylogic International
Author-email: developers@paylogic.com
License: MIT
Platform: UNKNOWN
